pancad/__about__.py
pancad/__init__.py
pancad/cad/freecad/__init__.py
pancad/cad/freecad/_application_types.py
pancad/cad/freecad/_bootstrap.py
pancad/cad/freecad/_constraint_translation.py
pancad/cad/freecad/_element_links.py
pancad/cad/freecad/_feature_mappers.py
pancad/cad/freecad/_feature_translation.py
pancad/cad/freecad/_filetypes.py
pancad/cad/freecad/_map_typing.py
pancad/cad/freecad/constants/__init__.py
pancad/cad/freecad/constants/_constraint_type.py
pancad/cad/freecad/constants/_edge_sub_parts.py
pancad/cad/freecad/constants/_geometry_list.py
pancad/cad/freecad/constants/_internal_alignment_type.py
pancad/cad/freecad/constants/_object_type.py
pancad/cad/freecad/constants/_pad_type.py
pancad/cad/freecad/constants/_sketch_numbers.py
pancad/config/__init__.py
pancad/config/config.toml
pancad/constants/__init__.py
pancad/constants/_angle_convention.py
pancad/constants/_config_cache_category.py
pancad/constants/_software_name.py
pancad/data/__init__.py
pancad/data/freecad.toml
pancad/filetypes/__init__.py
pancad/filetypes/part_file.py
pancad/geometry/__init__.py
pancad/geometry/abstract_feature.py
pancad/geometry/abstract_geometry.py
pancad/geometry/abstract_pancad_thing.py
pancad/geometry/circle.py
pancad/geometry/conversion.py
pancad/geometry/coordinate_system.py
pancad/geometry/ellipse.py
pancad/geometry/extrude.py
pancad/geometry/feature_container.py
pancad/geometry/line.py
pancad/geometry/line_segment.py
pancad/geometry/plane.py
pancad/geometry/point.py
pancad/geometry/sketch.py
pancad/geometry/spatial_relations.py
pancad/geometry/constants/__init__.py
pancad/geometry/constants/enum_constraint_reference.py
pancad/geometry/constants/enum_feature_type.py
pancad/geometry/constants/enum_sketch_constraint.py
pancad/geometry/constraints/__init__.py
pancad/geometry/constraints/_generator.py
pancad/geometry/constraints/abstract_constraint.py
pancad/geometry/constraints/distance.py
pancad/geometry/constraints/snapto.py
pancad-0.0.1.dist-info/METADATA
pancad-0.0.1.dist-info/WHEEL
pancad-0.0.1.dist-info/licenses/LICENSE
pancad-0.0.1.dist-info/RECORD
