Metadata-Version: 2.4
Name: pancad
Version: 0.0.1
Summary: A CAD (Computer-Aided Design) file translator
Project-URL: Homepage, https://github.com/spky/pancad
Project-URL: Issues, https://github.com/spky/pancad/issues
Author: spky
Maintainer: spky
License-Expression: CC0-1.0
License-File: LICENSE
Requires-Dist: numpy-quaternion==2024.0.10
Requires-Dist: numpy==2.2.1
Requires-Dist: scipy==1.16.1
